smiles_validator/__init__.py
smiles_validator/validator.py
smiles_validator-0.2.2.dist-info/licenses/LICENSE
smiles_validator-0.2.2.dist-info/METADATA
smiles_validator-0.2.2.dist-info/WHEEL
smiles_validator-0.2.2.dist-info/top_level.txt
smiles_validator-0.2.2.dist-info/RECORD
